<?xml version="1.0" encoding="UTF-8"?>
<objects serializationModel="Studio.02.01.00">
	<object class="AudioFile" id="{23e2a69e-c1a2-4828-95f9-caa27996b68e}">
		<property name="assetPath">
			<value>Briefs/Brief_Map_M_2_2_U1_SD.ogg</value>
		</property>
		<property name="isStreaming">
			<value>true</value>
		</property>
		<property name="frequencyInKHz">
			<value>44.0999985</value>
		</property>
		<property name="channelCount">
			<value>2</value>
		</property>
		<property name="length">
			<value>14.957233560090703</value>
		</property>
		<relationship name="masterAssetFolder">
			<destination>{0ca164d3-6648-4315-aa0f-efba1bfdc463}</destination>
		</relationship>
	</object>
</objects>
