<?xml version="1.0" encoding="UTF-8"?>
<objects serializationModel="Studio.02.01.00">
	<object class="AudioFile" id="{e640e98c-a1cb-4305-8318-61c6c98e0688}">
		<property name="assetPath">
			<value>Briefs/Brief_final_fhd_SD.ogg</value>
		</property>
		<property name="isStreaming">
			<value>true</value>
		</property>
		<property name="frequencyInKHz">
			<value>48</value>
		</property>
		<property name="channelCount">
			<value>2</value>
		</property>
		<property name="length">
			<value>82.38933333333334</value>
		</property>
		<relationship name="masterAssetFolder">
			<destination>{0ca164d3-6648-4315-aa0f-efba1bfdc463}</destination>
		</relationship>
	</object>
</objects>
